Workbook

Sheet Master
A1: Date | B1: Sales_volume | C1: Clothing_CPI | D1: Winter_Coats | E1: Summer_Dresses | F1: Black_Friday_Clothing | G1: School_Uniform
A2: 2015 JAN | B2: 82.7 | C2: 98 | D2: 7 | E2: 7 | F2: 0 | G2: 16
A3: 2015 FEB | B3: 79.5 | C3: 99.3 | D3: 4 | E3: 9 | F3: 0 | G3: 14
A4: 2015 MAR | B4: 87.2 | C4: 99.2 | D4: 2 | E4: 11 | F4: 0 | G4: 19
A5: 2015 APR | B5: 93.4 | C5: 99.9 | D5: 1 | E5: 15 | F5: 0 | G5: 22
A6: 2015 MAY | B6: 94.3 | C6: 100.5 | D6: 1 | E6: 13 | F6: 0 | G6: 18
A7: 2015 JUN | B7: 100.4 | C7: 100.1 | D7: 1 | E7: 16 | F7: 0 | G7: 28
A8: 2015 JUL | B8: 101.7 | C8: 96.7 | D8: 3 | E8: 13 | F8: 0 | G8: 39
A9: 2015 AUG | B9: 99.4 | C9: 98.2 | D9: 7 | E9: 7 | F9: 0 | G9: 67
A10: 2015 SEP | B10: 96 | C10: 100.9 | D10: 17 | E10: 3 | F10: 0 | G10: 41
A11: 2015 OCT | B11: 96.9 | C11: 102.9 | D11: 23 | E11: 2 | F11: 0 | G11: 16
A12: 2015 NOV | B12: 110 | C12: 102.8 | D12: 20 | E12: 2 | F12: 8 | G12: 15
A13: 2015 DEC | B13: 136.9 | C13: 101.5 | D13: 9 | E13: 2 | F13: 0 | G13: 12
... A133: 2025 DEC | B133: 133.3 | C133: 122 | D133: 11 | E133: 5 | F133: 1 | G133: 12

Sheet Data Dictionary
A1: Variable | B1: Description | C1: Source | D1: Unit
A2: Date | B2: Monthly observation period | C2: ONS / Google Trends | D2: Month-Year
A3: Sales_Volume | B3: Volume of sales in textile, clothing and footwear stores (non-seasonally adjusted) | C3: ONS Retail Sales Index | D3: Index
A4: Clothing_CPI | B4: Consumer Price Index for Clothing and Footwear (2015=100) | C4: ONS CPI Dataset | D4: Index
A5: Winter_Coats | B5: Google search interest for “winter coats” in the UK | C5: Google Trends | D5: 0–100
A6: Summer_Dresses | B6: Google search interest for “summer dresses” in the UK | C6: Google Trends | D6: 0–100
A7: Black_Friday_Clothing | B7: Google search interest for “black friday clothing” in the UK | C7: Google Trends | D7: 0–100
A8: School_Uniform | B8: Google search interest for “school uniform” in the UK | C8: Google Trends | D8: 0–100

Sheet chart2
A1: Date | B1: Clothing_CPI
A2: 2015 JAN | B2: 98
A3: 2015 FEB | B3: 99.3
A4: 2015 MAR | B4: 99.2
A5: 2015 APR | B5: 99.9
A6: 2015 MAY | B6: 100.5
A7: 2015 JUN | B7: 100.1
A8: 2015 JUL | B8: 96.7
A9: 2015 AUG | B9: 98.2
A10: 2015 SEP | B10: 100.9
A11: 2015 OCT | B11: 102.9
A12: 2015 NOV | B12: 102.8
A13: 2015 DEC | B13: 101.5
... A133: 2025 DEC | B133: 122

Sheet Chart3
A1: Date | B1: Winter_Coats | C1: Summer_Dresses | D1: School_Uniform
A2: 2015 JAN | B2: 7 | C2: 7 | D2: 16
A3: 2015 FEB | B3: 4 | C3: 9 | D3: 14
A4: 2015 MAR | B4: 2 | C4: 11 | D4: 19
A5: 2015 APR | B5: 1 | C5: 15 | D5: 22
A6: 2015 MAY | B6: 1 | C6: 13 | D6: 18
A7: 2015 JUN | B7: 1 | C7: 16 | D7: 28
A8: 2015 JUL | B8: 3 | C8: 13 | D8: 39
A9: 2015 AUG | B9: 7 | C9: 7 | D9: 67
A10: 2015 SEP | B10: 17 | C10: 3 | D10: 41
A11: 2015 OCT | B11: 23 | C11: 2 | D11: 16
A12: 2015 NOV | B12: 20 | C12: 2 | D12: 15
A13: 2015 DEC | B13: 9 | C13: 2 | D13: 12
... A133: 2025 DEC | B133: 11 | C133: 5 | D133: 12

Sheet Descriptive_Statistics
A1: Variable | B1: Mean | C1: Std. Dev. | D1: Min | E1: Max
A2: Sales_Volume | B2: =AVERAGE(Master!B2:B133) -> 95.801515 | C2: =_xlfn.STDEV.S(Master!B2:B133) -> 18.481453 | D2: =MIN(Master!B2:B133) -> 31.1 | E2: =MAX(Master!B2:B133) -> 144.7
A3: Clothing_CPI | B3: =AVERAGE(Master!C2:C133) -> 106.87727 | C3: =_xlfn.STDEV.S(Master!C2:C133) -> 7.9382021 | D3: =MIN(Master!C2:C133) -> 95.7 | E3: =MAX(Master!C2:C133) -> 122.6
A4: Winter_Coats | B4: =AVERAGE(Master!D2:D133) -> 9.0454545 | C4: =_xlfn.STDEV.S(Master!D2:D133) -> 8.3335647 | D4: =MIN(Master!D2:D133) -> 1 | E4: =MAX(Master!D2:D133) -> 33
A5: Summer_Dresses | B5: =AVERAGE(Master!E2:E133) -> 14.484848 | C5: =_xlfn.STDEV.S(Master!E2:E133) -> 11.52262 | D5: =MIN(Master!E2:E133) -> 2 | E5: =MAX(Master!E2:E133) -> 53
A6: Black_Friday_Clothing | B6: =AVERAGE(Master!F2:F133) -> 0.63636364 | C6: =_xlfn.STDEV.S(Master!F2:F133) -> 2.0648743 | D6: =MIN(Master!F2:F133) -> 0 | E6: =MAX(Master!F2:F133) -> 9
A7: School_Uniform | B7: =AVERAGE(Master!G2:G133) -> 30.068182 | C7: =_xlfn.STDEV.S(Master!G2:G133) -> 19.857198 | D7: =MIN(Master!G2:G133) -> 9 | E7: =MAX(Master!G2:G133) -> 100

Sheet Correlation
